bidobe/__init__.py
bidobe/astunit.py
bidobe/dobe.py
bidobe/orbit.py
bidobe/plotorb.py
bidobe-0.1.1.dist-info/METADATA
bidobe-0.1.1.dist-info/RECORD
bidobe-0.1.1.dist-info/WHEEL
bidobe-0.1.1.dist-info/top_level.txt
