Metadata-Version: 2.1
Name: bidobe
Version: 0.1.1
Summary: Doppler beaming simulation in binary systems.
Home-page: https://github.com/pbrus/binary-doppler-beaming
Author: Przemysław Bruś
License: UNKNOWN
Keywords: binary,doppler,beaming
Platform: UNKNOWN
Classifier: Development Status :: 5 - Production/Stable
Classifier: Intended Audience :: Science/Research
Classifier: License :: OSI Approved :: MIT License
Classifier: Operating System :: OS Independent
Classifier: Programming Language :: Python
Classifier: Programming Language :: Python :: 3.5
Classifier: Programming Language :: Python :: 3.6
Classifier: Programming Language :: Python :: 3.7
Classifier: Topic :: Scientific/Engineering :: Astronomy
Classifier: Topic :: Utilities
Requires-Dist: numpy
Requires-Dist: scipy
Requires-Dist: matplotlib
